[
  {
    "title": "What is Lorem Ipsum?",
    "url": "https://www.lipsum.com/",
    "id": 1
  },
  {
    "title": "What is Lorem Ipsum?",
    "url": "https://www.lipsum.com/",
    "id": 2
  },
  {
    "title": "What is Lorem Ipsum?",
    "url": "https://www.lipsum.com/",
    "id": 3
  },
  {
    "title": "What is Lorem Ipsum?",
    "url": "https://www.lipsum.com/",
    "id": 4
  },
  {
    "title": "What is Lorem Ipsum?",
    "url": "https://www.lipsum.com/",
    "id": 5
  },
  {
    "title": "What is Lorem Ipsum?",
    "url": "https://www.lipsum.com/",
    "id": 6
  },
  {
    "title": "What is Lorem Ipsum?",
    "url": "https://www.lipsum.com/",
    "id": 7
  },
  {
    "title": "What is Lorem Ipsum?",
    "url": "https://www.lipsum.com/",
    "id": 8
  },
  {
    "title": "What is Lorem Ipsum?",
    "url": "https://www.lipsum.com/",
    "id": 9
  },
  {
    "title": "What is Lorem Ipsum?",
    "url": "https://www.lipsum.com/",
    "id": 10
  }
]
